{
  "id": "W1628722779",
  "openalex_id": "https://openalex.org/W1628722779",
  "domain": "theology",
  "title": "Features of evaluation and self-evaluation of prosocial behaviour among fifth-and sixth-grade pupils",
  "year": 2015,
  "publication_date": "2015-01-01",
  "publication_month": "2015-01",
  "doi": "https://doi.org/10.5817/sp2015-1-5",
  "abstract": "Rozvoj prosoci\u00e1lnosti a v\u00fdchova charakteru s\u00fa jedn\u00fdmi z najv\u00fdznamnej\u0161\u00edch v\u00fdziev s\u00fa\u010dasnej \u0161koly. Cie\u013eom \u0161t\u00fadie, ktor\u00e1 je s\u00fa\u010das\u0165ou predprieskumnej f\u00e1zy \u0161ir\u0161ieho experiment\u00e1lneho sk\u00famania efektov etickej v\u00fdchovy, je zisti\u0165, ako \u017eiaci v kontexte tohto \u0161kolsk\u00e9ho predmetu vn\u00edmaj\u00fa vlastn\u00fa \u00farove\u0148 prosoci\u00e1lnosti, ako hodnotia svojich spolu\u017eiakov, ako ich hodnotia u\u010ditelia a \u010di s\u00fa medzi t\u00fdmito hodnoteniami zov\u0161eobecnite\u013en\u00e9 s\u00favislosti. Autori pou\u017eili revidovan\u00fa verziu Rocheho dotazn\u00edka prosoci\u00e1lneho spr\u00e1vania na vzorke 254 \u017eiakov (132 chlapcov) vo veku 10\u201312 rokov (piaty a \u0161iesty ro\u010dn\u00edk Z\u0160). V\u00fdsledky ukazuj\u00fa signifikantn\u00e9 rozdiely v sebahodnoten\u00ed aj hodnoten\u00ed druh\u00fdch, predov\u0161etk\u00fdm na z\u00e1klade pohlavia. Av\u0161ak nielen line\u00e1rne. U\u010ditelia hodnotia diev\u010dat\u00e1 ako prosoci\u00e1lnej\u0161ie, ne\u017e sa hodnotia ony samy, a naopak chlapcov hodnotia negat\u00edvnej\u0161ie, ne\u017e sa chlapci vidia sami. Chlapci sami sa hodnotia prosoci\u00e1lnej\u0161ie, ne\u017e ich vidia ostatn\u00ed, u diev\u010dat sa tento nepomer str\u00e1ca. Vek, v porovnan\u00ed 5-tych a 6-tych ro\u010dn\u00edkov, zohr\u00e1va zrete\u013en\u00fa rolu najm\u00e4 u u\u010dite\u013eov, ktor\u00ed signifikantne pozit\u00edvnej\u0161ie vn\u00edmaj\u00fa mlad\u0161\u00edch \u017eiakov. \u00daplnos\u0165 rodiny (die\u0165a \u017eije v dom\u00e1cnosti s matkou aj otcom) ako premenn\u00e1 neukazuje evidentn\u00e9 rozdiely vo vn\u00edman\u00ed \u017eiakov v porovnan\u00ed so situ\u00e1ciou, ke\u010f die\u0165a b\u00fdva len s matkou. Av\u0161ak v pr\u00edpade, ke\u010f die\u0165a \u017eije len s otcom, jeho sebavn\u00edmanie prosoci\u00e1lnosti je zna\u010dne negat\u00edvnej\u0161ie, ne\u017e je ono vn\u00edman\u00e9 ostatn\u00fdmi.",
  "pdf_url": "https://journals.phil.muni.cz/studia-paedagogica/article/download/18977/15033",
  "text": "Studia paedagogica\nro\u010d. 20, \u010d. 1, rok 2015\nwww.studiapaedagogica.cz\nDOI: 10.5817/SP2015-1-5\n \nCHARAKTERISTIKY HODNOTENIA \nA SEBAHODNOTENIA PROSOCI\u00c1LNEHO \nSPR\u00c1VANIA U \u017dIAKOV PIATYCH  \nA \u0160IESTYCH RO\u010cN\u00cdKOV VYBRAN\u00ddCH \nZ\u00c1KLADN\u00ddCH \u0160K\u00d4L\nFEATURES OF EVALUATION  \nAND SELF-EVALUATION  \nOF PROSOCIAL BEHAVIOUR AMONG  \nFIFTH- AND SIXTH-GRADE PUPILS\nMARTIN BRESTOVANSK\u00dd, ANNA S\u00c1DOVSK\u00c1,  \nPETER KUS\u00dd, IVAN PODMANICK\u00dd\nAbstrakt\nRozvoj prosoci\u00e1lnosti a v\u00fdchova charakteru s\u00fa jedn\u00fdmi z najv\u00fdznamnej\u0161\u00edch v\u00fdziev s\u00fa\u010dasnej \u0161koly. Cie\u013eom \n\u0161t\u00fadie, ktor\u00e1 je s\u00fa\u010das\u0165ou predprieskumnej f\u00e1z y \u0161ir\u0161ieho experiment\u00e1lneho sk\u00famania efektov etickej v\u00fdchovy, \nje zisti\u0165, ako \u017eiaci v kontexte tohto \u0161kolsk\u00e9ho predmetu vn\u00edmaj\u00fa vlastn\u00fa \u00farove\u0148 prosoci\u00e1lnosti, ako hodno-\ntia svojich spolu\u017eiakov, ako ich hodnotia u\u010ditelia a \u010di s\u00fa medzi t\u00fdmito hodnoteniami zov\u0161eobecnite\u013en\u00e9 \ns\u00favislosti. Autori pou\u017eili revidovan\u00fa verziu Rocheho dotazn\u00edka prosoci\u00e1lneho spr\u00e1vania na vzorke \n254 \u017eiakov (132 chlapcov) vo veku 10\u201312 rokov (piaty a \u0161iesty ro\u010dn\u00edk Z\u0160). V\u00fdsledky ukazuj\u00fa signifikant-\nn\u00e9 rozdiely v sebahodnoten\u00ed aj hodnoten\u00ed druh\u00fdch, predov\u0161etk\u00fdm na z\u00e1klade pohlavia. Av\u0161ak nielen line\u00e1r-\nne. U\u010ditelia hodnotia diev\u010dat\u00e1 ako prosoci\u00e1lnej\u0161ie, ne\u017e sa hodnotia ony samy, a naopak chlapcov hodnotia \nnegat\u00edvnej\u0161ie, ne\u017e sa chlapci vidia sami. Chlapci sami sa hodnotia prosoci\u00e1lnej\u0161ie, ne\u017e ich vidia ostatn\u00ed, \nu diev\u010dat sa tento nepomer str\u00e1ca. Vek, v porovnan\u00ed 5-tych a 6-tych ro\u010dn\u00edkov, zohr\u00e1va zrete\u013en\u00fa rolu najm\u00e4 \nu u\u010dite\u013eov, ktor\u00ed signifikantne pozit\u00edvnej\u0161ie vn\u00edmaj\u00fa mlad\u0161\u00edch \u017eiakov. \u00daplnos\u0165 rodiny (die\u0165a \u017eije v dom\u00e1c-\nnosti s matkou aj otcom) ako premenn\u00e1 neukazuje evidentn\u00e9 rozdiely vo vn\u00edman\u00ed \u017eiakov v porovnan\u00ed so \nsitu\u00e1ciou, ke\u010f die\u0165a b\u00fdva len s matkou. Av\u0161ak v pr\u00edpade, ke\u010f die\u0165a \u017eije len s otcom, jeho sebavn\u00edmanie \nprosoci\u00e1lnosti je zna\u010dne negat\u00edvnej\u0161ie, ne\u017e je ono vn\u00edman\u00e9 ostatn\u00fdmi.\nK\u013e\u00fa\u010dov\u00e9 slov\u00e1\nprosoci\u00e1lne spr\u00e1vanie, etick\u00e1 v\u00fdchova, mravn\u00e1 v\u00fdchova, sebahodnotenie\n\n68\nM. BRESTOVANSK\u00dd, A. S\u00c1DOVSK\u00c1, P. KUS\u00dd, I. PODMANICK\u00dd\nAbstract\nProsocial development and character education are those of highest important challenges for contemporary \nschool. The aim of present study is to examine how pupils perceive their own prosociality, how they evaluate \nthe classmates, what are the assessements made by teachers, and whether there is a coherency between them \nwhich could be enounced in general. The study is part of a wider experimental research plan focused on the \neffects of ethics education in pre-research phase. Authors used the revised version of Roche\u2018s Prosocial Behaviour \nScale (1998) for school population of 254 fifth and sixth grade\u2018s pupils (132 boys) in the age from 10 to 12. \nResults show significant differences in self-perception and other-percetion mainly based upon sex, not linear \nonly. Teachers perceive the girls as more prosocial than the girls perceive themselves, and by contrast teachers \nevaluate the boys more negatively than the boys see themselves. In general, boys consider themselves more \nprosocial than they are seen by others; by girls this inadequacy disappears. If compare the age, 5th and \n6th grade respectively, the strongest differences were investigated in group of teachers who perceive the \nyounger pupils significantly more prosocial. Family situation plays role when a child lives only with father. \nIn this case a child self-perception of prosociality is strongly worse than it is percepted by others.\nKeywords\nprosocial behaviour, ethics education, moral education, self-evaluation\nKontext\nV\u00fdvin prosoci\u00e1lnosti prebieha zv\u00e4\u010d\u0161a inform\u00e1lne, v podmienkach rodinn\u00fdch \n\u010di rovesn\u00edckych vz\u0165ahov. V kontexte humaniz\u00e1cie \u0161kolsk\u00fdch syst\u00e9mov sa v\u0161ak \nu\u017e d\u00e1vnej\u0161ie za\u010dali rodi\u0165 intencion\u00e1lne v\u00fdchovn\u00e9 programy priamo podpo-\nruj\u00face jej rozvoj (Berkowitz, 1997; Carr & Steutel, 1999; Solomon, Watson, \n& Battistich, 2001; Lickona, Shaps, & Lewis, 2003; Wynne & Ryan, 1993; \nRoche, 1992 a i.). Jednou z najmas\u00edvnej\u0161\u00edch aplik\u00e1ci\u00ed v\u00fdchovy zameranej na \nprosoci\u00e1lnos\u0165 vo form\u00e1lnom prostred\u00ed je koncepcia etickej v\u00fdchovy realizo-\nvan\u00e1 na Slovensku od roku 1992 (porov. Lencz, 1994). Predmet Etick\u00e1 v\u00fd-\nchova je zaraden\u00fd v \u0161t\u00e1tnom vzdel\u00e1vacom programe ako povinne volite\u013en\u00fd, \nalternuj\u00faci s n\u00e1bo\u017eenskou v\u00fdchovou, s hodinovou t\u00fd\u017edennou dot\u00e1ciou od \n1. po 8. ro\u010d. z\u00e1kladn\u00fdch \u0161k\u00f4l a na gymn\u00e1zi\u00e1ch a s hodinovou dvojt\u00fd\u017edennou \ndot\u00e1ciou pre 9. ro\u010d. z\u00e1kladn\u00fdch \u0161k\u00f4l a 1. ro\u010d. stredn\u00fdch \u0161k\u00f4l. Realizuje sa tak \npribli\u017ene na 90 % slovensk\u00fdch \u0161k\u00f4l. Z v\u00fdskumn\u00e9ho h\u013eadiska teda ide \no unik\u00e1tne prostredie (bohat\u00e9 na d\u00e1ta) pre pochopenie mo\u017enost\u00ed v\u00fdchovy \nk prosoci\u00e1lnosti vo form\u00e1lnych podmienkach \u0161koly. \nEtick\u00e1 v\u00fdchova a v\u00fdskum prosoci\u00e1lneho spr\u00e1vania\nNapriek dlhoro\u010dnej realiz\u00e1cii v\u0161ak existuje len minimum systematick\u00fdch \nv\u00fdstupov, ktor\u00e9 by referovali o efektoch tohto v\u00fdchovn\u00e9ho programu. Pred-\npoklad\u00e1me, \u017ee dan\u00fd stav je d\u00f4sledkom nieko\u013ek\u00fdch pr\u00ed\u010din. Na jednej strane \n\n69\nCHARAKTERISTIKY HODNOTENIA A SEBAHODNOTENIA \nv\u00fdchova je komplexn\u00fd fenom\u00e9n, ktor\u00fd sa len ve\u013emi \u0165a\u017eko d\u00e1 vtesna\u0165 do \nscientometrick\u00fdch parametrov v zmysle dosahovania v\u00fdkonmi pomenovate\u013e-\nn\u00fdch v\u00fdstupov.1 Plat\u00ed tie\u017e, \u017ee \u201ekauzalita be\u017en\u00e1 v pr\u00edrodn\u00fdch ved\u00e1ch je diametr\u00e1lne \nodli\u0161n\u00e1 od kauzality vo ved\u00e1ch soci\u00e1lnych\u201c (\u0160va\u0159\u00ed\u010dek, 2013, s. 59). Ak\u00e9ko\u013evek kvan-\ntifikovanie v\u00fdchovn\u00e9ho potenci\u00e1lu ur\u010dit\u00e9ho programu alebo intervencie je \nteda nutne ohrani\u010den\u00e9 konkr\u00e9tnymi podmienkami, v ktor\u00fdch sa realizuje, \nnajm\u00e4 osobnos\u0165ou vychov\u00e1vate\u013ea (Podmanick\u00fd & Szeliga, 2009) a \u017eiaka \n(Bierhoff, Klein, & Kramp, 1991; Bierhoff & Rohmann, 2004; Oliner & \nOliner, 1988; Penner, Fritzsche, Craiger, & Freifeld, 1995 a i.), ale aj mno\u017e-\nstvom mnoh\u00fdch \u010fal\u0161\u00edch premenn\u00fdch, vr\u00e1tane kult\u00fary prostredia (Barr & \nHigginsov\u00e1, 2007). Uvedomujeme si, \u017ee aj d\u00e1ta, ktor\u00e9 prezentujeme v aktu\u00e1l- \nnej \u0161t\u00fadii, podliehaj\u00fa t\u00fdmto z\u00e1konitostiam. \u010eal\u0161\u00edm probl\u00e9mom je samotn\u00fd \npojem prosoci\u00e1lneho spr\u00e1vania a uva\u017eovania, ktor\u00fd sa \u0161iroko horizont\u00e1lne \na vertik\u00e1lne vrstv\u00ed. Ide o mno\u017estvo r\u00f4znorod\u00fdch praktick\u00fdch prejavov ako \nnapr. pom\u00e1hanie, delenie sa, \u00fatecha, potvrdenie a pozit\u00edvne ocenenie druh\u00e9-\nho, pozorn\u00e9 po\u010d\u00favanie, empatia, solidarita (horizont\u00e1lna rovina) (porov. \nEisenberg, Fabes, & Spinrad, 2007; Roche & Sol, 1998; Wispe, 1972 a i.), ale \naj o kvalitat\u00edvnu r\u00f4znorodos\u0165, teda pre\u017e\u00edvanie a zd\u00f4vod\u0148ovanie prosoci\u00e1lne-\nho spr\u00e1vania (vertik\u00e1lna rovina) (Bierhoff, 2002; Carlo & Randall, 2001; \nEisenberg, Guthrie, Murphy, Shepard, Cumberland, & Carlo, 1999 a i.). \nV detailoch o t\u00fdchto metodologick\u00fdch ot\u00e1zkach pojedn\u00e1va na inom mieste \nBrestovansk\u00fd (2014). Napokon, pragmatick\u00fdm probl\u00e9mom v\u00fdskumu je kva-\nlita realiz\u00e1cie samotn\u00e9ho programu \u2013 v praxi plat\u00ed, \u017ee nie v\u0161etci u\u010ditelia s\u00fa \nodborne pripraven\u00ed v \u0161pecializ\u00e1cii predmetu etick\u00e1 v\u00fdchova. V ide\u00e1lnom \npr\u00edpade ide o absolventov odboru (mo\u017enos\u0165 \u0161t\u00fadia pon\u00faka p\u00e4\u0165 slovensk\u00fdch \nuniverz\u00edt), ale m\u00f4\u017ee \u00eds\u0165 aj o absolventov roz\u0161iruj\u00facej kvalifik\u00e1cie prostred-\nn\u00edctvom metodick\u00fdch centier, \u010di dokonca celkom nekvalifikovan\u00fdch \nu\u010dite\u013eov. Riadite\u013e z person\u00e1lnych d\u00f4vodov pridel\u00ed predmet u\u010dite\u013eovi s inou \nkvalifik\u00e1ciou. Tieto skuto\u010dnosti (skryt\u00e9 premenn\u00e9) m\u00f4\u017eu z\u00e1sadne deformova\u0165 \nefektivitu programu a v\u00fdskum ich mus\u00ed prec\u00edzne identifikova\u0165 a filtrova\u0165, \npri\u010dom vznik\u00e1 relevantn\u00e1 ot\u00e1zka, \u010di je to v\u00f4bec vy\u010derp\u00e1vaj\u00faco mo\u017en\u00e9.\n\t\nSamotn\u00e1 koncepcia je postaven\u00e1 na dlhodob\u00fdch v\u00fdskumoch aspektov \nprosoci\u00e1lnosti (Roche, 1992), ktor\u00e9 boli zasa motivovan\u00e9 \u0161ir\u0161\u00edm v\u00fdskumom \nfaktorov pozit\u00edvneho v\u00fdvinu charakteru (Ryan & Lickona, 1992 a i.). Roche \ntvrd\u00ed, \u017ee rozhoduj\u00facim pre rozvoj dobr\u00e9ho charakteru je pr\u00e1ve prosoci\u00e1lne \n1\t\nNapriek tomu existuje s\u00fastavn\u00fd politick\u00fd a legislat\u00edvny tlak na preformulov\u00e1vanie \nv\u00fdchovn\u00fdch cie\u013eov v ofici\u00e1lnych didaktick\u00fdch dokumentoch do v\u00fdkonov\u00fdch form\u00e1tov.\n\n70\nspr\u00e1vanie. Identifikoval desa\u0165 z\u00e1kladn\u00fdch faktorov, ktor\u00e9 treba rozv\u00edja\u0165 na \nstrane die\u0165a\u0165a, a p\u00e4\u0165 charakterist\u00edk pr\u00edstupu k die\u0165a\u0165u zo strany u\u010dite\u013ea, \u010do \ntvorilo z\u00e1klad jeho programu v\u00fdchovy k prosoci\u00e1lnosti (viac porov. Roche, \n1992). Tento bol po ist\u00fdch \u00faprav\u00e1ch prevzat\u00fd, metodicky a obsahovo roz\u0161\u00ed-\nren\u00fd (o etick\u00e9 aplika\u010dn\u00e9 t\u00e9my) a tak aplikovan\u00fd na Slovensku. Prirodzene \nteda jednou z prv\u00fdch \u0161t\u00fadi\u00ed efektov v\u00fdchovy k prosoci\u00e1lnosti bola experi-\nment\u00e1lna \u0161t\u00fadia L. Lencza (1991) v r\u00e1mci pilotn\u00e9ho overovania programu \nvznikaj\u00facej etickej v\u00fdchovy, ktorej z\u00e1very boli \u201eve\u013emi povzbudzuj\u00face\u201c (s. 4). \nKoubekov\u00e1 (1994) sk\u00famala p\u00f4sobenie programu v\u00fdchovy k prosoci\u00e1lnosti \nna osobnos\u0165 \u017eiakov dvojro\u010dn\u00fdm experiment\u00e1lnym overovan\u00edm s pou\u017eit\u00edm \nBianchiho Dotazn\u00edka prosoci\u00e1lnych tendenci\u00ed \u2013 DX (1990) v kombin\u00e1cii \ns mnoh\u00fdmi \u010fal\u0161\u00edmi n\u00e1strojmi (Dotazn\u00edka sebaocenenia /Pope, Craighead, \n& McHale, 1988/; \u0161k\u00e1la soci\u00e1lneho spr\u00e1vania /Kagan & Knight, 1981/; \ndotazn\u00edk empatie /Mehrabian & Ebstein, 1972/; test osobnosti CTP /Thorpe, \nClark, & Tiegs, 1953/; \u0161k\u00e1la rodinn\u00e9ho prostredia /Harga\u0161ov\u00e1 & Koll\u00e1rik, \n1986/ a dotazn\u00edk agresivity /Buss & Durke, 1957/). Uk\u00e1zala \u0161tatisticky v\u00fd-\nznamn\u00e9 zv\u00fd\u0161enie \u00farovne seba\u00facty, a to u v\u0161etk\u00fdch \u017eiakov, vr\u00e1tane 1. kontrol- \nnej skupiny, ktor\u00fa tvorili na programe nez\u00fa\u010dastnen\u00ed spolu\u017eiaci (2. kontroln\u00fa \nskupinu tvorili \u017eiaci inej \u0161koly). Toto zlep\u0161enie sa prejavilo aj v lep\u0161ej kvalite \n\u201evz\u00e1jomn\u00fdch interakci\u00ed, priate\u013eskej\u0161ej atmosf\u00e9re, v\u00e4\u010d\u0161ej satur\u00e1cii soci\u00e1lnych potrieb, potrieb \nuznania, prijatia a akcept\u00e1cie\u201c (s. 209). V kontexte realiz\u00e1cie projektu etickej \nv\u00fdchovy v \u010ceskej republike, ktor\u00fd je in\u0161pirovan\u00fd slovensk\u00fdm modelom, \ntie\u017e prib\u00fadaj\u00fa pr\u00e1ce zameran\u00e9 na experiment\u00e1lne overovanie jeho efektov. \nVan\u011bk (2011) pre tento \u00fa\u010del vyu\u017eil bat\u00e9riu nasleduj\u00facich n\u00e1strojov: \u0160k\u00e1lu \nseba\u00facty (Blatn\u00fd & Oseck\u00e1, 1994; Rosenberg, 1965), Dotazn\u00edk na\u0161a trieda \n(MCI, Fisher, & Fraser, 1981; La\u0161ek & Mare\u0161, 1991), spom\u00ednan\u00fd Dotazn\u00edk \nprosoci\u00e1lnych tendenci\u00ed (Bianchi) a nomina\u010dn\u00fa vrstovn\u00edcku techniku. \nV\u00fdsledky jeho v\u00fdskumu vyk\u00e1zali \u201ev\u00fdrazn\u00e9 zlep\u0161enie vo v\u00e4\u010d\u0161ine sledovan\u00fdch premen-\nn\u00fdch\u201c, najm\u00e4 \u201espokojnos\u0165 v triede, s\u00fadr\u017enos\u0165 \u017eiakov medzi sebou navz\u00e1jom, \u00farove\u0148 \nsebahodnotenia \u017eiakov a mieru v\u00fdskytu prosoci\u00e1lneho spr\u00e1vania\u201c (2012, s. 18). Moty\u010d-\nka (2013, s. 81) v\u00fdstupy svojho experimentu (337 \u017eiakov z 11 \u0161k\u00f4l) nehodno-\nt\u00ed tak jednozna\u010dne pozit\u00edvne. Napr. nie experiment\u00e1lna, ale kontroln\u00e1 skupi-\nna vyk\u00e1zala v postestoch \u0161tatisticky v\u00fdznamn\u00fd n\u00e1rast pomoci. \u201eD\u00f4vodom m\u00f4\u017ee \nby\u0165 skuto\u010dnos\u0165, \u017ee v r\u00e1mci etickej v\u00fdchovy s\u00fa \u017eiaci veden\u00ed k pomerne hlbokej reflexii \nsvojich sk\u00fasenost\u00ed\u201c (s. 118). T\u00e1 v po\u010diato\u010dn\u00fdch f\u00e1zach intencion\u00e1lnej mor\u00e1lnej \nv\u00fdchovy zvy\u0161uje citlivos\u0165 na mieru realizovanej pomoci (a in\u00fdch prosoci\u00e1l- \nnych prejavov) a napom\u00e1ha tie\u017e rastu sebakritiky. Prekvapiv\u00e9 nepriazniv\u00e9 \nv\u00fdsledky m\u00f4\u017eu by\u0165 jednoducho v\u00fdsledkom toho, \u017ee konat\u00edvny rozvoj je tu \npredbiehan\u00fd kognit\u00edvnym. V Lenczov\u00fdch experimentoch tak\u00fdto fenom\u00e9n \nzaznamenan\u00fd nebol.\nM. BRESTOVANSK\u00dd, A. S\u00c1DOVSK\u00c1, P. KUS\u00dd, I. PODMANICK\u00dd\n\n71\n\t\nZ pedagogick\u00e9ho h\u013eadiska je efekt\u00edvne tak pre samotn\u00fd z\u00e1kladn\u00fd v\u00fdskum \nako aj pre evalv\u00e1ciu praxe presne pomenova\u0165 konkr\u00e9tne prejavy prosoci\u00e1l-\nnosti, ktor\u00e9 o\u010dak\u00e1vame, \u017ee sa bud\u00fa programom rozv\u00edja\u0165. V\u00fdskumn\u00e9 n\u00e1stroje \nby mali zodpoveda\u0165 \u0161trukt\u00fare programu, \u010di dokonca konkr\u00e9tnym u\u010debn\u00fdm \npl\u00e1nom v danom ro\u010dn\u00edku (porov. Lencz & Kri\u017eov\u00e1, 1997). E\u0161te predt\u00fdm je \nv\u0161ak z metodologick\u00e9ho h\u013eadiska potrebn\u00e9 v\u00f4bec zisti\u0165 rozdiely vo vn\u00edman\u00ed \ntoho, \u010do je pova\u017eovan\u00e9 za prosoci\u00e1lne (obsah pojmu v kognit\u00edvnom obraze \nrespondentov) a tendencie v sebahodnoten\u00ed a hodnoten\u00ed druh\u00fdch. \nVn\u00edmanie a sebavn\u00edmanie prosoci\u00e1lnosti\nJe zn\u00e1me, ide o jedno z najpotvrdzovanej\u0161\u00edch zisten\u00ed v soci\u00e1lnej psychol\u00f3gii, \n\u017ee \u013eudia si v\u00e4\u010d\u0161inou prisudzuj\u00fa vy\u0161\u0161ie kvality ne\u017e ostatn\u00fdm, resp. ne\u017e prie-\nmeru popul\u00e1cie. Zvl\u00e1\u0161\u0165 to plat\u00ed v oblasti mravnosti a soci\u00e1lnosti. Ak s\u00fa aj \nochotn\u00ed uzna\u0165 niekomu vy\u0161\u0161iu \u0161pecifick\u00fa zru\u010dnos\u0165 alebo inteligenciu, \u201elen \nve\u013emi \u0165a\u017eko akceptuj\u00fa, \u017ee in\u00ed s\u00fa prosoci\u00e1lnej\u0161\u00ed ne\u017e oni sami\u201c (Fetchenhauer & \nDunning, 2006). Etick\u00e1 v\u00fdchova, ako uva\u017eoval vy\u0161\u0161ie spomenut\u00fd Moty\u010dka \n(2013), m\u00f4\u017ee vies\u0165 v prvej f\u00e1ze predov\u0161etk\u00fdm a pr\u00e1ve k form\u00e1cii sebavn\u00edma-\nnia a mor\u00e1lnej senzibiliz\u00e1cii, ktor\u00e1 sa prirodzene men\u00ed na z\u00e1klade \u017eivotn\u00e9ho \n\u0161t\u00fdlu a preferenci\u00ed. Merania v r\u00e1mci ro\u010dn\u00fdch experimentov tak ob\u010das dosa-\nhuj\u00fa opa\u010dn\u00e9 ne\u017e o\u010dak\u00e1van\u00e9 v\u00fdsledky, a to z d\u00f4vodu, \u017ee s\u00fa \u017eiaci citlivej\u0161\u00ed na \nto, \u010do je a \u010do nie je mor\u00e1lne alebo prosoci\u00e1lne.\n\t\nFetchenhauer a Dunning (2013) analyzuj\u00fa systematick\u00fd chybn\u00fd predsudok \no vlastnej mor\u00e1lnej a soci\u00e1lnej nadpriemernosti z troch perspekt\u00edv \u2013 motiv\u00e1-\ncie na z\u00e1klade tendencie posil\u0148ova\u0165 alebo utvrdzova\u0165 vlastn\u00e9 sebavedomie, \nna z\u00e1klade kult\u00farneho vplyvu (z\u00e1padnej priemyselnej spolo\u010dnosti) a napokon \nako evolucionistick\u00e9 vysvetlenie (explanation) v r\u00e1mci funkcie spr\u00e1vneho \nrozhodovania. Warden, Cheyne, Christie, Fitzpatrick a Reid (2003) pomeno-\nvali konkr\u00e9tnej\u0161ie procesy mor\u00e1lneho posudzovania druh\u00fdch. Medzi in\u00fdm \nzistili, \u017ee deti maj\u00fa tendenciu viac sa vyjadrova\u0165 k antisoci\u00e1lnemu ako pro-\nsoci\u00e1lnemu spr\u00e1vaniu; prosoci\u00e1lne deti aplikuj\u00fa pr\u00edsnej\u0161ie krit\u00e9ri\u00e1 pri hodno-\nten\u00ed spr\u00e1vania druh\u00fdch; diev\u010dat\u00e1 s\u00fa presved\u010den\u00e9, \u017ee diev\u010dat\u00e1 sa vo v\u0161eobec-\nnosti sk\u00f4r spr\u00e1vaj\u00fa prosoci\u00e1lne ne\u017e chlapci; chlapci veria, \u017ee obe pohlavia s\u00fa \nvyrovnan\u00e9, \u010do sa t\u00fdka uskuto\u010d\u0148ovania prosoci\u00e1lnych \u010dinov. Ot\u00e1zkou zost\u00e1va, \nako sa tieto tendencie prejavia priamo v kontexte etickej v\u00fdchovy a ako s\u00fa \nna ne pripraven\u00ed z poh\u013eadu presnosti percepcie u\u010ditelia etickej v\u00fdchovy. \nTie\u017e plat\u00ed, \u017ee prosoci\u00e1lne spr\u00e1vanie v r\u00e1mci \u0161kolsk\u00e9ho intencion\u00e1lneho pro-\ngramu rastie v\u00fdraznej\u0161ie, ak sebapercepcia \u0161tudenta v oblasti \u00farovne proso-\nci\u00e1lnosti \u010do najtesnej\u0161ie lad\u00ed s t\u00fdm, ako je vn\u00edman\u00fd ostatn\u00fdmi spolu\u017eiakmi \n(Armstrong, 2011). Ale pozit\u00edvne sebahodnotenie v oblasti prosoci\u00e1lnosti \nm\u00e1 aj v\u00fdznamn\u00e9 pozit\u00edva. \nCHARAKTERISTIKY HODNOTENIA A SEBAHODNOTENIA \n\n72\nRozdiely v hodnoten\u00ed a sebahodnoten\u00ed miery prosoci\u00e1lneho spr\u00e1vania\nCie\u013eom tejto \u0161t\u00fadie je zisti\u0165, \u010di existuj\u00fa signifikantn\u00e9 rozdiely v sebahodno-\nten\u00ed prosoci\u00e1lnosti u \u017eiakov 5. a 6. ro\u010dn\u00edkov z\u00e1kladn\u00fdch \u0161k\u00f4l (10\u201312 rokov), \nktor\u00ed bud\u00fa nesk\u00f4r respondentmi hlavnej \u0161t\u00fadie, v porovnan\u00ed s ich rovesn\u00edkmi \na u\u010dite\u013emi, a \u010di je mo\u017en\u00e9 vyslovi\u0165 ur\u010dit\u00e9 z\u00e1konitosti/tendencie v sebahodno-\nten\u00ed a hodnoten\u00ed druh\u00fdch. Prezentovan\u00e9 v\u00fdsledky s\u00fa s\u00fa\u010das\u0165ou pilotn\u00e9ho \noverovania v r\u00e1mci dlhodobej\u0161ieho experiment\u00e1lneho pl\u00e1nu. Kompletn\u00fd \npredprieskumn\u00fd dizajn tvorila bat\u00e9ria vz\u00e1jomne sa dop\u013a\u0148aj\u00facich n\u00e1strojov \npre v\u00fdskum prosoci\u00e1lnosti tak, aby pokryli jednak vy\u0161\u0161ie spomenut\u00e9 peda-\ngogick\u00e9 ciele a z\u00e1rove\u0148 umo\u017e\u0148ovali validiz\u00e1ciu. Pre na\u0161u \u0161t\u00fadiu sme revido-\nvali dotazn\u00edk prosoci\u00e1lnosti (Roche & Sol, 1998), dotazn\u00edk prosoci\u00e1lneho \nmor\u00e1lneho uva\u017eovania (Carlo & Eisenbergov\u00e1, 1992), dotazn\u00edk noodynami-\nky (Popielski, 1994) a dotazn\u00edk interperson\u00e1lnej diagn\u00f3zy ICL (Leary, Laforge, \n& Suczek, 1954 in Ko\u017een\u00fd & Ganick\u00fd, 1976). V \u0161tandardizovanej z\u00fa\u017eenej \nforme sme vyu\u017eili 10polo\u017ekov\u00fd osobnostn\u00fd test TIPI (Gosling, Rentfrow, \n& Swann, 2003). \n\t\nV aktu\u00e1lnom \u010dl\u00e1nku rie\u0161ime v\u00fdstupy z dotazn\u00edka prosoci\u00e1lnosti, ktor\u00fd bol \nako jedin\u00fd distribuovan\u00fd v troch form\u00e1ch \u2013 sebahodnotenie (ja-forma), \nhodnotenie vybran\u00e9ho spolu\u017eiaka (on-forma) a hodnotenie ka\u017ed\u00e9ho \u017eiaka \nu\u010dite\u013eom etickej v\u00fdchovy (on-forma). Pri hodnoten\u00ed spolu\u017eiaka i\u0161lo o n\u00e1hod-\nn\u00e9 losovanie, ka\u017ed\u00fd \u017eiak hodnotil pr\u00e1ve jedn\u00e9ho spolu\u017eiaka. Dotazn\u00edk \nvznikol selekciou z bohat\u00e9ho invent\u00e1ra popisuj\u00faceho konkr\u00e9tne prejavy pro-\nsoci\u00e1lneho spr\u00e1vania v troch kontextoch \u2013 \u0161kola, letn\u00fd t\u00e1bor, \u0161port (Roche \n& Sol, 1998, s. 17\u201325). Polo\u017eky kop\u00edruj\u00fa spom\u00ednan\u00fa horizont\u00e1lnu klasifik\u00e1ciu \ndesiatich typov prejavov: fyzick\u00e1 pomoc, fyzick\u00e1 slu\u017eba, podelenie sa, verb\u00e1lna \npomoc, \u00fatecha, potvrdenie a pozit\u00edvne ocenenie druh\u00e9ho, pozorn\u00e9 po\u010d\u00favanie, \nempatia, solidarita, pozit\u00edvna \u00fa\u010das\u0165 a jednota. Napr. kateg\u00f3riu \u201efyzick\u00e1 slu\u017e-\nba\u201c zastupuje (v kontexte \u0161kolskej triedy) v\u00fdpove\u010f \u201eNech\u00e1 svoje veci v triede \nupratan\u00e9, aby u\u013eah\u010dil pr\u00e1cu t\u00fd\u017edenn\u00edkom\u201c, kateg\u00f3riu \u201epodelenie sa\u201c s\u00fdtia medzi \nin\u00fdmi aj polo\u017eky \u201eDovol\u00ed kamar\u00e1tom pou\u017e\u00edva\u0165 svoje veci a hry\u201c alebo \u201eOpisuje svojim \npriate\u013eom r\u00f4zne osobn\u00e9 z\u00e1\u017eitky\u201c at\u010f. Ku ka\u017edej polo\u017eke sa respondent vyjadroval \nna \u0161k\u00e1le 1 (\u00faplne s\u00fahlas\u00edm) \u2013 4 (v\u00f4bec nes\u00fahlas\u00edm). Ani jedna polo\u017eka nebo-\nla formulovan\u00e1 negat\u00edvne. V kone\u010dnom s\u00fa\u010dte teda \u010d\u00edm ni\u017e\u0161ie sk\u00f3re, t\u00fdm \nvy\u0161\u0161ia miera prosoci\u00e1lnosti. P\u00f4vodn\u00fdch 40 polo\u017eiek (v\u017edy 4 zastupovali \njednu kateg\u00f3riu) sme zo psychohygienick\u00fdch d\u00f4vodov redukovali na 21. \nSelekciu vypracov\u00e1vali nez\u00e1visle traja v\u00fdskumn\u00edci, a\u017e potom sa sna\u017eili dospie\u0165 \nk zhode. Okrem z\u00e1kladn\u00e9ho pravidla zachova\u0165 v\u017edy dve (v jednom pr\u00edpade \ntri) polo\u017eky na kateg\u00f3riu do \u00favahy brali najm\u00e4 zrozumite\u013enos\u0165 polo\u017eky na \nz\u00e1klade pilotn\u00fdch rozhovorov face-to-face s vo\u013ene vybran\u00fdmi z\u00e1stupcami \ndanej vekovej skupiny. Napr. z kateg\u00f3rie Pozorn\u00e9 po\u010d\u00favanie sme polo\u017eku \u201eMl\u010d\u00ed, \nzakia\u013e in\u00fd rozpr\u00e1va\u201c uprednostnili pred polo\u017ekou \u201eDopo\u010d\u00fava a\u017e do konca\u201c, ktor\u00e1 \nM. BRESTOVANSK\u00dd, A. S\u00c1DOVSK\u00c1, P. KUS\u00dd, I. PODMANICK\u00dd\n\n73\nje menej jasn\u00e1. Polo\u017eku \u201eZost\u00e1va zameran\u00fd na d\u00f4vody diskusie, ak je to mo\u017en\u00e9\u201c sme \nz d\u00f4vodu komplikovanej \u0161tylistiky vyl\u00fa\u010dili at\u010f.2 \u010co sa t\u00fdka z\u00e1kladn\u00e9ho \nmetodologick\u00e9ho pr\u00edstupu, ide o n\u00e1ro\u010dn\u00e9 rozl\u00ed\u0161enie a komplikovan\u00fa ot\u00e1zku. \nAk\u00e1ko\u013evek dotazn\u00edkov\u00e1 met\u00f3da (\u010di u\u017e sebariportn\u00e1 alebo s hodnoten\u00edm) bola \nv\u00fdsledkom hodnotenia v\u0161etk\u00fdch \u0161tudentov navz\u00e1jom. Tak\u00fdto model je krajne \nn\u00e1ro\u010dn\u00fd na realiz\u00e1ciu. Preto sa \u0161t\u00fadia viac zaober\u00e1 pr\u00e1ve rozpormi v hodno-\nteniach troch skup\u00edn (ja, on, u\u010dite\u013e). Na druhej strane kvantitat\u00edvny dizajn na \ndostato\u010dnej vzorke m\u00f4\u017ee vies\u0165 aj k z\u00e1verom o samotnom spr\u00e1van\u00ed, preto\u017ee \nhodnotenia z tohto uhla poh\u013eadu objektivizuje.\n\t\nZber d\u00e1t pre predv\u00fdskum bol realizovan\u00fd v janu\u00e1ri/febru\u00e1ri 2014 na vzor-\nke 254 \u017eiakov (132 chlapcov) piatych (150) a \u0161iestych (104) tried z\u00e1kladn\u00fdch \n\u0161k\u00f4l z\u00e1padn\u00e9ho Slovenska (mimo Bratislavy).3 V\u00fdber vzorky prebiehal prie-\nbe\u017ene na z\u00e1klade ochoty jednotliv\u00fdch participuj\u00facich u\u010dite\u013eov spolupracova\u0165.4 \nBola dodr\u017ean\u00e1 podmienka, aby \u017eiaci nav\u0161tevovali pravidelne hodiny etickej \nv\u00fdchovy. \u017diaci s\u00fa zo \u0161iestich \u0161k\u00f4l r\u00f4znej ve\u013ekosti a z odli\u0161n\u00fdch demografick\u00fdch \nkontextov (stredne ve\u013ek\u00e9 mesto/nad 60 000 obyv., men\u0161ie mesto, dedina). \nV\u00fdskumu sa z\u00fa\u010dastnili cel\u00e9 triedne skupiny (presnej\u0161ie tie \u010dasti, v ktor\u00fdch \nsa vyu\u010duje etick\u00e1 v\u00fdchova). P\u00f4vodn\u00e1 vzorka mala vy\u0161\u0161iu po\u010detnos\u0165, no nie- \nktor\u00ed u\u010ditelia odmietli vypl\u0148ova\u0165 hodnotenia \u017eiakov, ke\u010f\u017ee to pova\u017eovali za \npr\u00edli\u0161 za\u0165a\u017euj\u00face. I\u0161lo o menej ako 15 % respondentov a z\u00e1kladn\u00fa sociode-\nmografick\u00fa \u0161trukt\u00faru to nenaru\u0161ilo. Kon\u0161truktov\u00e1 a obsahov\u00e1 validita sa \nopiera o v\u00fdskumn\u00fa pr\u00e1cu Rocheho Olivara, pri\u010dom dotazn\u00edk je kon\u0161truova-\nn\u00fd pre \u0161kolsk\u00e9 prostredie. Preto aj vykazuje nie dostato\u010dne vysok\u00e9 korel\u00e1cie \ns vybran\u00fdmi polo\u017ekami interperson\u00e1lneho dotazn\u00edka ICL v kateg\u00f3ri\u00e1ch \n(r = 0,23). Kriteri\u00e1lna validita doposia\u013e nebola preuk\u00e1zan\u00e1, n\u00e1stroj nebol \n\u0161tandardizovan\u00fd (viac pozri Brestovansk\u00fd et al., 2014).\n\t\nIntern\u00e1 reliabilita bola po\u010d\u00edtan\u00e1 na ka\u017ed\u00fa formu zvl\u00e1\u0161\u0165. Pre sebahodno-\ntenie bolo Cronbachovo alfa 0,839 (N = 205); pre hodnotenie od spolu\u017eiaka \nCronbachovo alfa = 0,908 (N = 252); pre hodnotenie od u\u010dite\u013ea Cronbacho-\nvo alfa = 0,942 (N = 254). Ni\u017e\u0161ie uv\u00e1dzame tie\u017e z\u00e1kladn\u00e9 frekven\u010dn\u00e9 cha-\nrakteristiky v jednotliv\u00fdch skupin\u00e1ch (sebahodnotenie graf 1, tab. 1; hodno-\ntenie od spolu\u017eiaka graf 2, tab. 2; hodnotenie od u\u010dite\u013ea graf 3, tab. 3). \nVzh\u013eadom na \u0161k\u00e1lu (1\u20134) a po\u010det polo\u017eiek (21) sa teoreticky celkov\u00e9 sk\u00f3re \nmohlo pohybova\u0165 v rozmedz\u00ed od 21\u201384 bodov.\n2\t\nFin\u00e1lna podoba dotazn\u00edka je k\u00a0dispoz\u00edcii u\u00a0prv\u00e9ho autora \u0161t\u00fadie.\n3\t\nV\u00a0s\u00falade s\u00a0delen\u00edm regi\u00f3nov Slovenska pod\u013ea met\u00f3dy Eurostatu (Bratislava, z\u00e1padn\u00e9, \nstredn\u00e9 a\u00a0v\u00fdchodn\u00e9 Slovensko).\n4\t\nNe\u0161lo len o poskytnutie priestoru pre zber d\u00e1t v predprieskume, ale aj o potenci\u00e1lnu \nspolupr\u00e1cu v hlavnom experiment\u00e1lnom pl\u00e1ne, ktor\u00fd zahr\u0148a metodick\u00e9 \u0161kolenia, \nkvalitat\u00edvne vstupy, pretesty a posttesty.\nCHARAKTERISTIKY HODNOTENIA A SEBAHODNOTENIA \n\n74\nGraf 1\nFrekvencie v sebahodnoten\u00ed\nTabu\u013eka 1\nFrekven\u010dn\u00e9 charakteristiky v sebahodnoten\u00ed\nFrekven\u010dn\u00e9 vlastnosti v sebahodnoten\u00ed \nN = 250, ch\u00fdbaj\u00face hodnoty: 4\nPriemer\n45,59\nM\u00f3dus\n46,00\n\u0160tandardn\u00e1 odch\u00fdlka\n8,82\n\u0160picatos\u0165\n2,27\n\u0160ikmos\u0165\n-1,07\nMinimum\n4,00\nMaximum\n62,00\nTabu\u013eka 2\nFrekven\u010dn\u00e9 charakteristiky v hodnoten\u00ed  \nod spolu\u017eiaka\nFrekven\u010dn\u00e9 vlastnosti v hodnoten\u00ed \nod spolu\u017eiaka \nN = 252, ch\u00fdbaj\u00face hodnoty: 2\nPriemer\n40,88\nM\u00f3dus\n43,00\n\u0160tandardn\u00e1 odch\u00fdlka\n13,24\n\u0160picatos\u0165\n0,22\n\u0160ikmos\u0165\n-0,75\nMinimum\n0,00\nMaximum\n63,00\nGraf 2 \nFrekvencie v hodnoten\u00ed od spolu\u017eiaka\nTabu\u013eka 3\nFrekven\u010dn\u00e9 charakteristiky v hodnoten\u00ed  \nod u\u010dite\u013eov\nFrekven\u010dn\u00e9 vlastnosti v hodnoten\u00ed  \nod u\u010dite\u013eov \nN = 254, ch\u00fdbaj\u00face hodnoty: 0\nPriemer\n44,27\nM\u00f3dus\n49,00\n\u0160tandardn\u00e1 odch\u00fdlka\n8,85\n\u0160picatos\u0165\n0,57\n\u0160ikmos\u0165\n-0,92\nMinimum\n15,00\nMaximum\n60,33\nGraf 3\nFrekvencie v hodnoten\u00ed od u\u010dite\u013eov\nM. BRESTOVANSK\u00dd, A. S\u00c1DOVSK\u00c1, P. KUS\u00dd, I. PODMANICK\u00dd\n\n75\nV\u00fdsledky\nZ\u00e1kladnou ot\u00e1zkou, ktorou z\u00e1rove\u0148 porovn\u00e1me na\u0161u \u0161t\u00fadiu s mnoh\u00fdmi in\u00fd- \nmi, je rozdielnos\u0165 \u00farovne prosoci\u00e1lnosti na z\u00e1klade pohlavia. Podobne, ako \npotvrdzuje Fabes a Eisenbergov\u00e1 (1998), u diev\u010dat je prosoci\u00e1lnos\u0165 vy\u0161\u0161ia ako \nu chlapcov. Plat\u00ed to aj transkult\u00farne (Carlo et al., 2001). Eisenbergov\u00e1 \net al. (2007) dop\u013a\u0148a, \u017ee \u201erozdiely v pohlav\u00ed boli signifikantne vy\u0161\u0161ie, ke\u010f bola prosoci\u00e1l-\nnos\u0165 meran\u00e1 sebariportn\u00fdmi met\u00f3dami alebo hodnoten\u00edm od druh\u00fdch, v porovnan\u00ed \ns met\u00f3dami pozorovania\u201c. V\u0161eobecne u \u017eien sa o\u010dak\u00e1va, \u017ee s\u00fa viac vn\u00edmav\u00e9, \nempatick\u00e9 a prosoci\u00e1lne ne\u017e mu\u017ei, zatia\u013e \u010do mu\u017ei s\u00fa viac nez\u00e1visl\u00ed a na cie\u013e \nzameran\u00ed (napr. Spence, Helmreich, & Stapp, 1974). Tie\u017e bolo zisten\u00e9, \u017ee hod-\nnotenia od u\u010dite\u013ea a rovesn\u00edka s\u00fa viac vyrovnan\u00e9 ne\u017e hodnotenia u\u010dite\u013ea \na seba, resp. rovesn\u00edka a seba (Ledingham et al., 1982; Pakaslahti & Keltikan-\ngas-J\u00e4rvinen, 2000 in Armstrong, 2011, s. 357). Ako ukazuje tab. 4, pohlavie \nje ve\u013emi silnou premennou pre prosoci\u00e1lne spr\u00e1vanie.\nTabu\u013eka 4\nRozdiely v priemeroch hodnoten\u00ed prosoci\u00e1lneho spr\u00e1vania na z\u00e1klade pohlavia\n \npohlavie\nN\npriemer \u0161tandardn\u00e1 \nodch\u00fdlka\nt\nrozdiel  \nv priemeroch\nsebahodnotenie\n \nchlapci\n132\n40,87\n9,06\n4,58**\n4,88\ndiev\u010dat\u00e1\n122\n35,99\n7,80\nhodnotenie od spolu\u017eiaka \nchlapci\n132\n48,30\n14,13\n6,73**\n10,46\ndiev\u010dat\u00e1\n122\n37,84\n10,13\nhodnotenie od u\u010dite\u013ea \nchlapci\n132\n43,33\n11,95\n8,34**\n11,00\ndiev\u010dat\u00e1\n122\n32,33\n8,65\n** p < 0,001\nVo v\u0161etk\u00fdch troch form\u00e1ch vych\u00e1dzaj\u00fa v\u00fdznamn\u00e9 signifikantn\u00e9 rozdiely \nv prospech diev\u010dat, najviac ale u u\u010dite\u013eov (pozri graf 4). Polo\u017eka PROS_U \nznamen\u00e1 mieru hodnotenia prosoci\u00e1lnosti, ako ju vn\u00edmali u\u010ditelia u jednot-\nliv\u00fdch \u017eiakov (chlapci = 1, diev\u010dat\u00e1 = 2). E\u0161te raz pripom\u00edname, \u010d\u00edm ni\u017e\u0161ie \n\u010d\u00edslo, t\u00fdm vy\u0161\u0161ia miera prosoci\u00e1lnosti. Graf ukazuje silne odli\u0161n\u00e9 rozlo\u017eenie \nhodnotenia a tie\u017e extr\u00e9mnej\u0161ie spektrum hodn\u00f4t.\nCHARAKTERISTIKY HODNOTENIA A SEBAHODNOTENIA \n\n76\n1 22\n13 2\nN =\nP O H L\n2 ,0 0\n1 ,0 0\nP R O S _ U\n8 0\n7 0\n6 0\n5 0\n4 0\n3 0\n2 0\n1 0\nGraf 4\nRozdiely v hodnoten\u00ed od u\u010dite\u013eov na z\u00e1klade pohlavia\nUveden\u00e9 z\u00e1rove\u0148 otv\u00e1ra ot\u00e1zku, \u010di u\u010ditelia neprid\u00e1vaj\u00fa do hodnotenia stereo- \ntyp pohlavia e\u0161te v\u00fdraznej\u0161ie ne\u017e samotn\u00ed \u017eiaci. Ako ukazuje nasleduj\u00faca \ntabu\u013eka (tab. 5), naozaj u\u010ditelia hodnotia diev\u010dat\u00e1 signifikantne ako proso- \nci\u00e1lnej\u0161ie, ne\u017e sa hodnotia ony samy, a naopak, chlapcov hodnotia negat\u00edv-\nnej\u0161ie, ne\u017e sa chlapci vidia sami.\nTabu\u013eka 5\nRozdiely v hodnoten\u00ed od u\u010dite\u013eov\npohlavie\n \nN\npriemer\n\u0161tandardn\u00e1 \nodch\u00fdlka\nt\nrozdiel\nv priemeroch\nchlapci\nsebahodnotenie\n132\n40,87\n9,06\n-2,246*\n-2,46\n \nhodnotenie od u\u010dite\u013ea\n132\n43,33\n11,95\ndiev\u010dat\u00e1\nsebahodnotenie\n122\n35,99\n7,80\n4,435**\n3,66\n \nhodnotenie od u\u010dite\u013ea\n122\n32,33\n8,65\n* p < 0,05, ** p < 0,001\nIn\u00fdmi slovami, chlapci sa spravidla pova\u017euj\u00fa za podstatne prosoci\u00e1lnej\u0161\u00edch, \nne\u017e ich vid\u00ed okolie. U diev\u010dat tento rozdiel mizne, \u010do sa potvrdzuje aj v po-\nrovnan\u00ed sebahodnotenia s hodnoten\u00edm od spolu\u017eiakov (tab. 6).\nM. BRESTOVANSK\u00dd, A. S\u00c1DOVSK\u00c1, P. KUS\u00dd, I. PODMANICK\u00dd\n\n77\nTabu\u013eka 6\nRozdiely v sebahodnoten\u00ed a hodnoten\u00ed od spolu\u017eiakov na z\u00e1klade pohlavia\npohlavie  \npriemer\nN\n\u0161tandardn\u00e1 \nodch\u00fdlka\nt\nrozdiely \nv priemeroch\nchlapci\nsebahodnotenie\n40,87\n132\n9,06\n-6,06**\n-7,42\nhodnotenie od spolu\u017eiakov\n48,30\n132\n14,13\ndiev\u010dat\u00e1\nsebahodnotenie\n35,99\n122\n7,80\n-1,86*\n-1,84\nhodnotenie od spolu\u017eiakov\n37,84\n122\n10,13\n* p < 0,10, ** p < 0,001\nZ h\u013eadiska veku najm\u00e4 u u\u010dite\u013eov zohr\u00e1va efekt nastupuj\u00facich piatakov jed-\nnozna\u010dn\u00fa \u00falohu. K\u00fdm u samotn\u00fdch det\u00ed, \u010di u\u017e v sebahodnoten\u00ed alebo vo \nvn\u00edman\u00ed druh\u00fdch, nedoch\u00e1dza k zvl\u00e1\u0161tnym v\u00fdkyvom, u u\u010dite\u013ea by sme moh-\nli hovori\u0165 a\u017e o efekte \u201emil\u00e9ho piata\u010dika\u201c. Predov\u0161etk\u00fdm chlapcov hodnotia \nu\u010ditelia ako v\u00fdrazne prosoci\u00e1lnej\u0161\u00edch v porovnan\u00ed len s o rok star\u0161\u00edmi \u0161ies-\ntakmi (t = 2,76, p < 0,05). Pravdepodobne u\u010ditelia stoto\u017e\u0148uj\u00fa discipl\u00ednu \na podriadenie sa autorite, ktor\u00e9 je zjavn\u00e9 u piatakov \u2013 nov\u00e1\u010dikov na druhom \nstupni, s prosoci\u00e1lnym spr\u00e1van\u00edm. V tomto zmysle aj diev\u010dat\u00e1 nap\u013a\u0148aj\u00fa lep\u0161ie \nrolov\u00e9 o\u010dak\u00e1vania (porov. tab. 7).\nTabu\u013eka 7\nRozdiely v hodnoten\u00ed na z\u00e1klade pohlavia\npohlavie\n \nro\u010dn\u00edk\nN\npriemer\n\u0161tandardn\u00e1 \nodch\u00fdlka\nchlapci\nsebahodnotenie\n5\n70\n40,71\n9,70\n \n6\n59\n40,78\n8,43\nhodnotenie od spolu\u017eiakov\n5\n71\n47,25\n14,54\n \n6\n60\n48,72\n13,40\nhodnotenie od u\u010dite\u013ea\n5\n72\n40,78*\n11,89\n \n6\n60\n46,38*\n11,38\ndiev\u010dat\u00e1\nsebahodnotenie\n5\n77\n35,13\n8,01\n \n \n6\n44\n37,32\n7,29\n \nhodnotenie od spolu\u017eiakov\n5\n77\n37,29\n10,74\n \n \n6\n44\n39,05\n8,98\n \nhodnotenie od u\u010dite\u013ea\n5\n78\n31,54\n8,98\n \n \n6\n44\n33,73\n7,94\n* p < 0,05\nCHARAKTERISTIKY HODNOTENIA A SEBAHODNOTENIA \n\n78\nRodinn\u00e9 z\u00e1zemie zohr\u00e1va v hodnoten\u00ed prosoci\u00e1lnosti det\u00ed \u0161pecifick\u00fa \u00falohu. \nZd\u00e1 sa, \u017ee na samotn\u00fa prosoci\u00e1lnos\u0165 nem\u00e1 vplyv to, \u010di die\u0165a \u017eije s obomi \nrodi\u010dmi alebo len s matkou. Extr\u00e9mny moment sme zaznamenali v pr\u00edpade, \n\u017ee die\u0165a b\u00fdva doma len s otcom. Kv\u00f4li n\u00edzkemu po\u010dtu tak\u00fdchto pr\u00edpadov \n(N = 3, t.j. jeden chlapec, dve diev\u010dat\u00e1) nem\u00f4\u017eeme hovori\u0165 o \u0161tatistickom \npotvrden\u00ed, no upozor\u0148ujeme na zjavn\u00e9 probl\u00e9my v sebapercepcii \u2013 sebahod-\nnotenie tak\u00fdchto det\u00ed je v\u00fdrazne ni\u017e\u0161ie ne\u017e ich hodnotenie od spolu\u017eiakov \n(ktor\u00e9 bolo nadpriemerne pozit\u00edvne) (tab. 8).\nTabu\u013eka 8\nHodnotenie prosoci\u00e1lnosti vzh\u013eadom na rodinn\u00e9 z\u00e1zemie\nrodina\nN\npriemer\n\u0161tandardn\u00e1 \nodch\u00fdlka\nsebahodnotenie\nb\u00fdvam s oboma rodi\u010dmi\n192\n38,67\n8,76\n \nb\u00fdvam len s matkou\n55\n37,36\n7,91\nb\u00fdvam len s otcom\n3\n53,33\n18,15\nhodnotenie od spolu\u017eiakov\nb\u00fdvam s oboma rodi\u010dmi\n192\n42,82\n13,26\n \nb\u00fdvam len s matkou\n55\n44,64\n14,11\nb\u00fdvam len s otcom\n3\n36,33\n2,31\nhodnotenie od u\u010dite\u013ea\nb\u00fdvam s oboma rodi\u010dmi\n192\n37,88\n11,55\n \nb\u00fdvam len s matkou\n55\n37,97\n11,99\nb\u00fdvam len s otcom\n3\n42,33\n19,66\nDiskusia\nV \u010desko-slovenskom prostred\u00ed doposia\u013e nebol realizovan\u00fd v\u00fdskum proso- \nci\u00e1l-neho spr\u00e1vania s dan\u00fdmi v\u00fdskumn\u00fdmi n\u00e1strojmi, ktor\u00e9 by komparovali \nsebahodnotenie s hodnoten\u00edm druh\u00fdch a triangulovali by zistenia s hodno-\nteniami od u\u010dite\u013eov. Naj\u010dastej\u0161ie sa dop\u013a\u0148aj\u00fa zistenia o aspektoch prosoci\u00e1l- \nneho spr\u00e1vania sociometrick\u00fdmi d\u00e1tami (\u010cavojov\u00e1, Belovi\u010dov\u00e1, & Sirota, \n2011; Van\u011bk, 2011; Moty\u010dka, 2013), tie v\u0161ak prirodzene nemo\u017eno stoto\u017e\u0148ova\u0165 \ns prosoci\u00e1lnos\u0165ou. \n\t\nZjavn\u00fdm je rozdiel v hodnoten\u00ed prosoci\u00e1lneho spr\u00e1vania na z\u00e1klade veku \nu u\u010dite\u013eov. Piatakov vidia jednozna\u010dne pozit\u00edvnej\u0161ie ne\u017e \u0161iestakov, no pri \nsebahodnoten\u00ed a hodnoten\u00ed spolu\u017eiaka kateg\u00f3ria veku nezohr\u00e1va rolu. \nNaproti tomu v meta-anal\u00fdze Eisenbergovej a Fabesa (1998 in Eisenberg, \n2007) sa ukazuje opa\u010dn\u00fd trend \u2013 adolescenti (13\u201315 rokov) maj\u00fa tendenciu \nby\u0165 prosoci\u00e1lnej\u0161\u00ed ne\u017e deti vo veku 7\u201312 rokov. Tie\u017e star\u0161\u00ed adolescenti \n(16\u201318 rokov) s\u00fa prosoci\u00e1lnej\u0161\u00ed ne\u017e \u017eiaci element\u00e1rnych \u0161k\u00f4l (Fabes, Carlo, \nKupanoff, & Laible, 1999). Pri interpret\u00e1cii tohto rozporu treba ale bra\u0165 do \nM. BRESTOVANSK\u00dd, A. S\u00c1DOVSK\u00c1, P. KUS\u00dd, I. PODMANICK\u00dd\n\n79\n\u00favahy konkr\u00e9tne typy prosoci\u00e1lneho spr\u00e1vania. Napr. pomoc obetiam agre-\nsie m\u00f4\u017ee klesa\u0165 po\u010das adolescencie (Lindeman, Harakka, & Keltikangas-\n-J\u00e6rvinen, 1997 in Eisenberg et al., 2007). V dotazn\u00edku pou\u017eit\u00e1 typol\u00f3gia \n(Roche & Sol, 1998) m\u00e1 amb\u00edciu zachyti\u0165 spr\u00e1vanie v \u0161kolskom prostred\u00ed. \nPravdepodobne tu plat\u00ed paralela s v\u00fdskumami hodnotenia prosoci\u00e1lnosti \nv rodine, kde rodi\u010dia vn\u00edmaj\u00fa prosoci\u00e1lne spr\u00e1vanie adolescentov cez ich \npomoc v dom\u00e1cnosti, teda prirodzene ako klesaj\u00facu v porovnan\u00ed s pred-\nch\u00e1dzaj\u00facim \u017eivotn\u00fdm obdob\u00edm (Eberly, Montemayor, & Flannery, 1993).\n\t\nZd\u00e1 sa, \u017ee u u\u010dite\u013eov existuje ak\u00fdsi spolo\u010dn\u00fd v\u00fdklad prosoci\u00e1lneho spr\u00e1-\nvania postaven\u00fd na stereotype \u201edobr\u00e9ho die\u0165a\u0165a\u201c prv\u00e9ho stup\u0148a z\u00e1kladnej \n\u0161koly a u\u010ditelia menej dok\u00e1\u017eu zareagova\u0165 na nov\u00e9 typy prosoci\u00e1lneho spr\u00e1-\nvania star\u0161\u00edch \u017eiakov.\n\t\nPodobn\u00fd probl\u00e9m sme zachytili aj v rozdieloch hodnotenia na z\u00e1klade \npohlavia. Je zn\u00e1me, \u017ee diev\u010dat\u00e1 s\u00fa spravidla hodnoten\u00e9 ako viac prosoci\u00e1lne \nne\u017e chlapci, ke\u010f\u017ee \u017eeny s\u00fa pova\u017eovan\u00e9 za viac zodpovedn\u00e9, empatick\u00e9, \nmaj\u00face tendencie ku vz\u0165ahom, zatia\u013e\u010do mu\u017ei za viac nez\u00e1visl\u00fdch a na v\u00fdkon \na \u00faspech zameran\u00fdch (porov. Hastings, Utendale, & Sullivan, 2007; Whiting \n& Edwards, 1973). Prv\u00ed spomenut\u00ed autori uk\u00e1zali, \u017ee tieto rozdiely s\u00fa aj trans- \nkult\u00farne. V na\u0161om v\u00fdskume v\u0161ak u\u010ditelia (presnej\u0161ie u\u010dite\u013eky \u2013 ani jeden \nz u\u010dite\u013eov etickej v\u00fdchovy, teda hodnotiaci, nebol mu\u017e) maj\u00fa tendenciu ten-\nto stereotyp e\u0161te posil\u0148ova\u0165. Objekt\u00edvne rozdiely zv\u00e4\u010d\u0161uj\u00fa na obe strany, \ndiev\u010dat\u00e1m body prid\u00e1vaj\u00fa a chlapcom uberaj\u00fa. Z meta\u0161t\u00fadie Fabesa a Eisen-\nbergovej (1998, s. 13\u201314) vypl\u00fdva, \u017ee \u201erozdiely v pohlav\u00ed boli signifikantne v\u00e4\u010d\u0161ie, \nke\u010f prosoci\u00e1lne odpovede boli meran\u00e9 sebariportn\u00fdmi met\u00f3dami alebo hodnoten\u00edm od \ndruh\u00fdch ne\u017e met\u00f3dami pozorovania\u201c. T\u00ed ist\u00ed autori tvrdia, \u017ee ve\u013ekos\u0165 efektu po-\nhlavia je v\u00e4\u010d\u0161\u00ed aj v z\u00e1vislosti od typu ukazovate\u013eov \u2013 v\u00e4\u010d\u0161ie rozdiely boli \nv kateg\u00f3ri\u00e1ch oh\u013eaduplnos\u0165/l\u00e1skavos\u0165, men\u0161ie v in\u0161trument\u00e1lnej pomoci, \n\u00fateche a delen\u00ed sa. V na\u0161om v\u00fdskume sa rozdiely javia kon\u0161tantn\u00e9 pri r\u00f4znych \npodtypoch prosoci\u00e1lneho spr\u00e1vania (vi\u010f spom\u00ednan\u00fa horizont\u00e1lnu klasifi- \nk\u00e1ciu desiatich typov, Roche & Sol, 1998).\n\t\nNapokon v\u00fdrazn\u00fdm, hoci v malom po\u010dte (n = 3), sa ukazuje vplyv rodinnej \nkon\u0161tel\u00e1cie na sebavn\u00edmanie ako prosoci\u00e1lneho. \u00daplnos\u0165 rodiny (die\u0165a \u017eije \nv dom\u00e1cnosti s matkou aj otcom) ako premenn\u00e1 neukazuje evidentn\u00e9 rozdie-\nly vo vn\u00edman\u00ed prosoci\u00e1lnosti u \u017eiakov v porovnan\u00ed so situ\u00e1ciou, ke\u010f die\u0165a \nb\u00fdva len s matkou. Av\u0161ak v pr\u00edpade, ke\u010f die\u0165a \u017eije len s otcom, jeho seba- \nvn\u00edmanie prosoci\u00e1lnosti je zna\u010dne pozit\u00edvnej\u0161ie, ne\u017e je ono vn\u00edman\u00e9 ostat-\nn\u00fdmi. Zd\u00e1 sa, \u017ee tu hr\u00e1 rolu nedostatok sebareflexie, ktor\u00fd sa vytr\u00e1ca nepr\u00ed-\ntomnos\u0165ou \u017eensk\u00e9ho vzoru, \u010di dokonca \u017eivotn\u00fd \u0161t\u00fdl ovplyvnen\u00fd nepodnetnos-\n\u0165ou v tejto oblasti zo strany otca. Zhou, Eisenberg, Losoya, Fabes, Reiser, \nGuthrie et al. (2002) takisto rozozn\u00e1vaj\u00fa ako k\u013e\u00fa\u010dov\u00fd najm\u00e4 vplyv matky na \nprosoci\u00e1lnos\u0165 die\u0165a\u0165a.\nCHARAKTERISTIKY HODNOTENIA A SEBAHODNOTENIA \n\n80\nZ\u00e1ver\nHlavn\u00fdm z\u00e1merom tohto pr\u00edspevku bolo poda\u0165 spr\u00e1vu o v\u00fdskume proso- \nci\u00e1lneho spr\u00e1vania, konkr\u00e9tne referova\u0165 o tendenci\u00e1ch v sebahodnoten\u00ed, \nv porovanan\u00ed s hodnoten\u00edm od druh\u00fdch, pri\u010dom sme prihliadali na r\u00f4zne \nnez\u00e1visl\u00e9 premenn\u00e9 (vek, pohlavie, s\u00fa\u017eitie v rodine). Implementovali sme do \nv\u00fdskumnej praxe nov\u00e9 v\u00fdskumn\u00e9 n\u00e1stroje a pop\u00edsali v\u00fdchodziu situ\u00e1ciu \nv \u00farovni prosoci\u00e1lneho spr\u00e1vania \u017eiakov 5. a 6. tried z\u00e1kladn\u00fdch \u0161k\u00f4l na \nSlovensku.\n\t\nNa\u0161e d\u00e1ta na jednej strane potvrdzuj\u00fa v\u00fdsledky viacer\u00fdch predch\u00e1dzaj\u00facich \nv\u00fdskumov. V kontexte etickej v\u00fdchovy postavenej na b\u00e1ze prosoci\u00e1lnosti \nv\u0161ak prin\u00e1\u0161aj\u00fa nieko\u013eko nov\u00fdch v\u00fdziev pre pedagogick\u00fd v\u00fdskum aj eduka\u010dn\u00fa \nprax. V prvom rade ide o ot\u00e1zku u\u010dite\u013esk\u00fdch stereotypov v nazeran\u00ed na pro-\nsoci\u00e1lnos\u0165 \u017eiakov z h\u013eadiska pohlavia. Pre\u010do s\u00fa podstatne v\u00fdraznej\u0161ie ne\u017e \nu samotn\u00fdch det\u00ed? Ako sa vyv\u00edja vz\u0165ah medzi vn\u00edman\u00edm discipl\u00edny a proso-\nci\u00e1lneho spr\u00e1vania u \u017eiakov? Existuje \u0161pecificky chlap\u010densk\u00e1 prosoci\u00e1lnos\u0165, \nktor\u00e1 nespad\u00e1 do kognit\u00edvneho r\u00e1mca be\u017ene pou\u017e\u00edvan\u00e9ho pre defin\u00edciu pro-\nsoci\u00e1lnosti? Ak\u00e9 postupy bud\u00fa funk\u010dn\u00e9 pre \u00fa\u010dinn\u00fa form\u00e1ciu prosoci\u00e1lnosti \nu chlapcov v prostred\u00ed \u0161koly? D\u00f4le\u017eit\u00e9 a pr\u00ednosn\u00e9 bude sk\u00fama\u0165 aj mo\u017enosti \nprenosu prosoci\u00e1lnej atrib\u00facie do rod\u00edn, najm\u00e4 ne\u00fapln\u00fdch, kde zostalo die\u0165a \ns otcom. Samotn\u00e9 zistenie je potrebn\u00e9 potvrdi\u0165 na dostato\u010dne \u0161irokej popu-\nl\u00e1cii. Akoko\u013evek, u\u017e sebaobraz, ktor\u00e9ho s\u00fa\u010das\u0165ou je prosoci\u00e1lnos\u0165, napom\u00e1-\nha zvy\u0161ovaniu prevalencie prosoci\u00e1lneho spr\u00e1vania. Prejaven\u00e9 pripisovanie \nprosoci\u00e1lnych charakterist\u00edk vedie ku konkr\u00e9tnemu prosoci\u00e1lnemu spr\u00e1vaniu \n(Jensen & Moore, 1977; Miller et al., 1975; Grusec, 1980 a i. in Roche, 1992). \nV\u00fdskum pokra\u010duje pretestom a n\u00e1slednou experiment\u00e1lnou f\u00e1zou, v ktorej \nnez\u00e1vislou premennou bude realizovan\u00fd program vo vybran\u00fdch experimen-\nt\u00e1lnych skupin\u00e1ch so spolupracuj\u00facimi u\u010dite\u013emi etickej v\u00fdchovy, pri\u010dom jeho \nefekty bud\u00fa porovn\u00e1van\u00e9 s kontrolnou skupinou \u017eiakov nezapojen\u00fdch tried.\nPo\u010fakovanie\n\u010cl\u00e1nok je v\u00fdstupom v r\u00e1mci projektu VEGA: Teoretick\u00e9 presk\u00famanie a empiric-\nk\u00e9 overenie konceptu prosoci\u00e1lnosti ako v\u00fdchodiskovej b\u00e1z y aktu\u00e1lnej koncepcie Etickej \nv\u00fdchovy v SR (\u010d\u00edslo 1/0962/13).\nM. BRESTOVANSK\u00dd, A. S\u00c1DOVSK\u00c1, P. KUS\u00dd, I. PODMANICK\u00dd\n\n81\nLiterat\u00fara\nArmstrong, C. (2011). The Impact of Self and Peer Perceptual Differences on Student Social \nBehaviour. British Journal of Educational Psychology, 81(3), 355\u2013368.\nBarr, J., & Higgins-D\u2019Alessandrov\u00e1, A. (2007). Adolescent Empathy and Prosocial Behavior \nin the Multidimensional Context of School Culture. The Journal of Genetic Psychology, 168(3), \n231\u2013250.\nBerkowitz, M. W. (1997). The Complete Moral Person: Anatomy and Formation. In J. M. Dubois, \nMoral Issues and Psychology: Personalist Contributions to Selected Problems. (s. 11\u201341). Lauhan MD: \nUniversity Press of America.\nBierhoff, H. W. (2002). Prosocial Behaviour. New York: Psychology Press.\nBierhoff, H. W., Klein, R., & Kramp, P. (1991). Evidence for the Altruistic Personality from \nData on Accident Research. Journal of Personality, 59(2), 263\u2013280. \nBierhoff, H. W., & Rohmann, E. (2004). Altruistic Personality in the Context of the Empathy\u2013\nAltruism Hypothesis. European Journal of Personality, 18(4), 351\u2013365.\nBrestovansk\u00fd, M. (2014). Metodologick\u00e9 ot\u00e1zky v\u00fdskumu prosoci\u00e1lnosti. In A. Rajsk\u00fd & \nI. Podmanick\u00fd, Prosoci\u00e1lnos\u0165 a etick\u00e1 v\u00fdchova. (s. 41\u201358). Trnava: VEDA. \nCarlo, G., Eisenberg, N., & Knight, G. P. (1992). An Objective Measure of Adolescents\u2019 \nProsocial Moral Reasoning. Journal of Research on Adolescence, 2(4), 331\u2013349.\nCarlo, G., Roesch, S. C., Knight, G. P., & Koller, S. H. (2001). Between or Within-culture \nVariation? Culture Group as a Moderator of the Relations Between Individual Differen- \nces and Resource Allocation Preferences. Journal of Applied Developmental Psychology, 22(6), \n559\u2013579.\nCarlo, G., & Randall, B. A. (2002). The Development of a Measure of Prosocial Behaviors \nfor Late Adolescents. Journal of Youth and Adolescence, 31(1), 31\u201344.\nCarr, D., & Steutel, J. (Eds.) (1999). Virtue Ethics and Moral Education. London: Routledge.\n\u010cavojov\u00e1, V., Belovi\u010dov\u00e1, Z., & Sirota, M. (2011). Mindreading and Empathy as Predictors \nof Prosocial Behavior. Studia psychologica, 53(4), 351\u2013362.\nEberly, M. B., Montemayor, R., & Flannery, D. J. (1993). Variation in Adolescent Helpfulness \nToward Parents In a Family Context. Journal of Early Adolescence, 13(3), 228\u2013244.\nEisenberg, N., Fabes, R. A., & Spinrad, T. L. (2006). Prosocial development. In N. Eisenberg \n(Vol. Ed.), W. Damon & R. M. Lerner (Series Eds.), Handbook of child psychology: Social, \nemotional, and personality development (Vol. 3, pp. 646\u2013718). New York: Wiley.\nEisenberg, N., Guthrie, I. K., Murphy, B. C., Shepard, S. A., Cumberland, A., & Carlo, G. \n(1999). Consistency and Development of Prosocial Dispositions: A Longitudinal Study. \nChild Development, 70(6), 1360\u20131372.\nFabes, R. A., & Eisenberg, N. (1998). Meta-Analyses of Age and Sex Differences in Children\u2019s \nand Adolescents\u2019 Prosocial Behavior. In W. Damon (Ed.), Handbook of Child Psychology, \nFifth Edition (Vol. 3: Social, Emotional, and Personality Development, N. Eisenberg \n[Ed.]).\nFabes, R. A., Carlo, G., Kupanoff, K., & Laible, D. (1999). Early Adolescence and Prosocial/\nmoral Behavior: The Role of Individual Processes. Journal of Early Adolescence, 19(1), 5\u201316.\nFetchenhauer, D., & Dunning, D. (2006). Perceptions of Prosociality and Solidarity in Self \nand Others. In D. Fetchenhauer et al. (Eds.), Solidarity and Prosocial Behavior. An Integration \nof Sociological and Psychological Perspectives. (s. 61\u201374). New York: Springer. \nCHARAKTERISTIKY HODNOTENIA A SEBAHODNOTENIA \n\n82\nGosling, S. D., Rentfrow, P. J., & Swann, W. B. (2003). A Very Brief Measure of the Big-Five \nPersonality Domains. Journal of Research in Personality, 37(6), 504\u2013528.\nHastings, P. D., Utendale, W., & Sullivan, C. (2007). The socialization of prosocial develop-\nment. In J. E. Grusec & P. D. Hastings (Eds.), Handbook of socialization (pp. 638\u2013664). New \nYork: Guildford Press.\nKoubekov\u00e1, E. (1994). P\u00f4sobenie programu v\u00fdchovy k prosoci\u00e1lnosti na osobnos\u0165 \u017eiakov \nz\u00e1kladn\u00fdch \u0161k\u00f4l. Psychol\u00f3gia a patapsychol\u00f3gia die\u0165a\u0165a, 29(3), 205\u2013215. \nKo\u017een\u00fd, J., & Ganick\u00fd, P. (1976). Pr\u00edru\u010dka pre Dotazn\u00edk interperson\u00e1lnej diagn\u00f3z y \u2013 ICL. Bratislava: \nPsychodiagnostick\u00e9 a didaktick\u00e9 testy.\nLencz, L. (1991). Bilancia a v\u00fdh\u013eady etickej v\u00fdchovy. U\u010dite\u013esk\u00e9 noviny, 30(2), 3\u20134.\nLencz, L. (1994). The Slovak Ethical Education Project. Cambridge Journal of Education, 24(3), \n443\u2013451.\nLencz, L., & Kri\u017eov\u00e1, O. (1997). U\u010debn\u00e9 osnovy etickej v\u00fdchovy pre 5. a\u017e 9. ro\u010dn\u00edk z\u00e1kladnej \u0161koly. \nDostupn\u00e9 z http://www2.statpedu.sk/Pedagogicke_dokumenty/Zakladne_skoly/Osnovy/\nETIKA. doc\nLickona, T., Schaps, E., & Lewis, C. (2003). CEP\u2019s Eleven Principles of Effective Character Edu-\ncation. Washington, DC: Character Education Partnership.\nMoty\u010dka, P. (2013). Implementace dopl\u0148uj\u00edc\u00edho vzd\u011bl\u00e1vac\u00edho oboru Etick\u00e1 v\u00fdchova v \u010cesk\u00e9 republice. \n(Dizerta\u010dn\u00e1 pr\u00e1ca). Pedagogick\u00e1 fakulta, Univerzita Karlova v Praze: Praha.\nOliner, S., & Oliner, P. (1988). The Altruistic Personality: Rescuers of Jews in Nazi Europe. New \nYork: Free Press.\nPenner, L. A., Fritzsche, B. A., Craiger, J. P., & Freifeld, T. R. (1995). Measuring the Proso-\ncial Personality. In J. Butcher & C. D. Spielberger (Eds.), Advances in Personality Assessment. \n(Vol. 10) (s. 147\u2013164). Hillsdale, NJ: LEA.\nPodmanick\u00fd, I., & Szeliga, P. (2009). Noetick\u00fd rozmer u\u010dite\u013ea etickej v\u00fdchovy. In Mravn\u00e1 \nv\u00fdchova v \u0161kol\u00e1ch na Slovensku a v zahrani\u010d\u00ed. Zborn\u00edk pr\u00edspevkov z medzin\u00e1rodnej vedeckej \nkonferencie. (s. 177\u2013184). Bansk\u00e1 Bystrica: Univerzita Mateja Bela.\nPopielski, K. (1994). Noetyczny Wymiar Osobowo\u015bci. Lublin: Redakcja Wydawnictw KUL.\nRoche, R. O. (1992). Etick\u00e1 v\u00fdchova. Bratislava: Orbis Pictus Istropolitana.\nRoche, R. O., & Sol, N. (1998). Educaci\u00f3n Prosocial de las Emociones, Valores y Actitudes positivas. \nBlume: Barcelona.\nRyan, K., & Lickona, T. (Eds.) (1992). Character Development in Schools and Beyond. 2nd edition. \nWashington, DC: The Council for Research in Values and Philosophy.\nSolomon, D., Watson, M. S., & Battistich, V. A. (2001). Teaching and Schooling Effects on \nMoral/prosocial Development. In V. Richardson (Ed.), Handbook of Research on Teaching. \n(s. 566\u2013603). Washington, DC: American Educational Research Association. \nSpence, J. T., Helmreich, R. L., & Stapp, J. (1974). The Personal Attributes Questionnaire: \nA Measure of Sex-role Stereotypes and Masculinity-femininity. JSAS: Catalog of Selected \nDocuments in Psychology, 4(1), 43\u201344.\n\u0160va\u0159\u00ed\u010dek, R. (2013). Konec pedagogiky: kritick\u00e1 esej. Studia paedagogica, 18(2\u20133), 55\u201372.\nVan\u011bk, D. (2011). Etick\u00e1 v\u00fdchova \u2013 mo\u017enost rozvoje prosoci\u00e1ln\u00edho chov\u00e1n\u00ed u \u017e\u00e1k\u016f 2. stupn\u011b \nz\u00e1kladn\u00ed \u0161koly. Experiment\u00e1ln\u00ed studie. Paidag\u00f3gos. 7(1), 28\u201341.\nWarden, D., Cheyne, B., Christie, D., Fitzpatrick, H., & Reid, K. (2003). Assessing Children\u2019s \nPerceptions of Prosocial and Antisocial Peer Behaviour. Educational Psycholog y, 23(5), \n547\u2013567.\nM. BRESTOVANSK\u00dd, A. S\u00c1DOVSK\u00c1, P. KUS\u00dd, I. PODMANICK\u00dd\n\n83\nWhiting, B. B., & Edwards, C. P. (1973). A Cross-cultural Analysis of Sex Differences in the \nBehavior of Children Aged 3 Through 11. Journal of Social Psychology, 91(2), 171\u2013188.\nWispe, L. G. (1972). Positive Forms of Social Behavior: An Overview. Journal of Social Issues, \n28(3), 1\u201319. \nWynne, E. A., & Ryan, K. (1993). Reclaiming Our Schools. A Handbook on Teaching Character, \nAcademics, and Discipline. New York: Merill.\nZhou, Q., Eisenberg, N., Losoya, S. H., Fabes, R. A., Reiser, M., Guthrie, I. K., & Shepard, \nS. A. (2002). The Relations of Parental Warmth and Positive Expressiveness to Children\u2019s \nEmpathy-Related Responding and Social Functioning: A Longitudinal Study. Child \nDevelopment, 73(3), 893\u2013915.\nKontakty na autorov\nMartin Brestovansk\u00fd\nKatedra pedagogick\u00fdch \u0161t\u00fadi\u00ed, Pedagogick\u00e1 fakulta, Trnavsk\u00e1 univerzita v Trnave\nE-mail: martin.brestovansky@truni.sk\nAnna S\u00e1dovsk\u00e1\nKatedra pedagogick\u00fdch \u0161t\u00fadi\u00ed, Pedagogick\u00e1 fakulta, Trnavsk\u00e1 univerzita v Trnave\nE-mail: anna.sadovska@truni.sk\nPeter Kus\u00fd\nKatedra pedagogick\u00fdch \u0161t\u00fadi\u00ed, Pedagogick\u00e1 fakulta, Trnavsk\u00e1 univerzita v Trnave\nE-mail: kusy@sasap.sk\nIvan Podmanick\u00fd\nKatedra pedagogick\u00fdch \u0161t\u00fadi\u00ed, Pedagogick\u00e1 fakulta, Trnavsk\u00e1 univerzita v Trnave\nE-mail: ivan.podmanicky@truni.sk\nCorresponding authors\nMartin Brestovansk\u00fd\nDepartment of Educational Studies, Faculty of Education, Trnava University in Trnava\nE-mail: martin.brestovansky@truni.sk\nAnna S\u00e1dovsk\u00e1\nDepartment of Educational Studies, Faculty of Education, Trnava University in Trnava\nE-mail: anna.sadovska@truni.sk\nPeter Kus\u00fd\nDepartment of Educational Studies, Faculty of Education, Trnava University in Trnava\nE-mail: kusy@sasap.sk\nIvan Podmanick\u00fd\nDepartment of Educational Studies, Faculty of Education, Trnava University in Trnava\nE-mail: ivan.podmanicky@truni.sk\nCHARAKTERISTIKY HODNOTENIA A SEBAHODNOTENIA"
}
