{
  "paper_id": "W2140902438",
  "domain": "computer_science",
  "variant": "improved",
  "text": "We introduce a C++ program, named Top++, for the numerical evaluation of the total inclusive cross-section for top-quark pair production at hadron colliders. The program gives precise prediction of the cross-section by using two complementary approaches: 1) a fixed-order calculation with exact Next-to-Next-to-Leading Order (NNLO) accuracy, and 2) a soft-gluon resummed prediction in Mellin space up to full Next-to-Next-to-Leading Logarithm (NNLL) accuracy.\n\nTop++ is a C++ program designed for fast and easy calculations of physical quantities at the TeV scale. There are 29 options which enable the user to freely change the physical parameters and calculation settings as needed. In short, Top++ is easy to use while preserving at the same time its full power as a fully customizable C++ program based on a physics-conceptual intuitive front-end that does not require any prior C++ programming knowledge. Top++ is an efficient program, requiring less than 200 MB of memory at run time, which is a standard quantity on modern PCs. It uses only standard external libraries like GSL and LHAPDF.\n\n**Program Summary**\n*   **Program Name:** Top++ (ver. 2.0)\n*   **Homepage:** http://www.alexandermitov.com/software\n*   **License:** GNU Public License\n*   **Language:** C++\n*   **Systems:** Linux, Mac OS X, and other Unix-like environments\nThe following libraries are available: SHMEM OpenMP POSIX Threads TBB GCC/CLANG Vectorized C/C++ External Libraries GSL, LHAPDF",
  "version": "3.2",
  "headline": "Fully Human Written",
  "prediction": "We believe that this document is fully human-written",
  "prediction_short": "Human",
  "fraction_ai": 0.0,
  "fraction_ai_assisted": 0.0,
  "fraction_human": 1.0,
  "num_ai_segments": 0,
  "num_ai_assisted_segments": 0,
  "num_human_segments": 1,
  "windows": [
    {
      "text": "We introduce a C++ program, named Top++, for the numerical evaluation of the total inclusive cross-section for top-quark pair production at hadron colliders. The program gives precise prediction of the cross-section by using two complementary approaches: 1) a fixed-order calculation with exact Next-to-Next-to-Leading Order (NNLO) accuracy, and 2) a soft-gluon resummed prediction in Mellin space up to full Next-to-Next-to-Leading Logarithm (NNLL) accuracy.\n\nTop++ is a C++ program designed for fast and easy calculations of physical quantities at the TeV scale. There are 29 options which enable the user to freely change the physical parameters and calculation settings as needed. In short, Top++ is easy to use while preserving at the same time its full power as a fully customizable C++ program based on a physics-conceptual intuitive front-end that does not require any prior C++ programming knowledge. Top++ is an efficient program, requiring less than 200 MB of memory at run time, which is a standard quantity on modern PCs. It uses only standard external libraries like GSL and LHAPDF.\n\n**Program Summary**\n*   **Program Name:** Top++ (ver. 2.0)\n*   **Homepage:** http://www.alexandermitov.com/software\n*   **License:** GNU Public License\n*   **Language:** C++\n*   **Systems:** Linux, Mac OS X, and other Unix-like environments\nThe following libraries are available: SHMEM OpenMP POSIX Threads TBB GCC/CLANG Vectorized C/C++ External Libraries GSL, LHAPDF",
      "label": "Human Written",
      "ai_assistance_score": 0.11401429027318954,
      "confidence": "Medium",
      "start_index": 0,
      "end_index": 1466,
      "word_count": 215,
      "token_length": 346
    }
  ]
}