{
  "paper_id": "W4236509319",
  "domain": "political_science",
  "variant": "new",
  "text": "A radical new exploration of the nature of war in the 21st century Global Policing Wars explores the dynamics of military intervention in the post-Cold War era through the prism of the US wars in Afghanistan and Iraq. Going beyond the level of military strategy and the politics of individual interventions, the book advances a new interdisciplinary approach that draws on social theory and philosophy to understand how war is imagined and practiced as part of liberal governance. Holmqvist argues that liberal politics and theory has redefined war and peace as an administrative matter of governance, an ongoing business of policing what it deems to be “abnormal” or “criminal” and “lawful” and “orderly”. The enemy, whose political legitimacy is contested, is reduced to a criminal who must be punished. The resulting “policing wars” is a new mode of war that operates beyond the conventional “war” vs. “peace” or “war” vs. “crime” oppositions and has been increasingly regularized in Western military doctrine and practice.\n\nLiberal Interventionism and Crisis Governance Scaffolding Time, Space and Power in the Liberal War on Terror tells the intellectual history of the liberal war on terror, from its roots in the liberal peace debate in the 1990s, through to the intervention in Afghanistan after 9/11, to contemporary governance in crisis contexts in Libya and Syria. By tracing this development of liberal war from its early stages, through to its fully fledged post-adversarial incarnation today, the book reveals the myth of a post-adversarial war and the unintended consequences this myth produces. Through a nuanced examination of the liberal imagination, Scaffolding Time, Space and Power in the Liberal War on Terror contributes to the emerging scholarship in the field of critical war studies by exploring the implications of the liberal imagination on the logics of organised violence in the contemporary world, and in so doing, sheds light on the evolution of global governance as a liberal project.",
  "version": "3.2",
  "headline": "Fully Human Written",
  "prediction": "We believe that this document is fully human-written",
  "prediction_short": "Human",
  "fraction_ai": 0.0,
  "fraction_ai_assisted": 0.0,
  "fraction_human": 1.0,
  "num_ai_segments": 0,
  "num_ai_assisted_segments": 0,
  "num_human_segments": 1,
  "windows": [
    {
      "text": "A radical new exploration of the nature of war in the 21st century Global Policing Wars explores the dynamics of military intervention in the post-Cold War era through the prism of the US wars in Afghanistan and Iraq. Going beyond the level of military strategy and the politics of individual interventions, the book advances a new interdisciplinary approach that draws on social theory and philosophy to understand how war is imagined and practiced as part of liberal governance. Holmqvist argues that liberal politics and theory has redefined war and peace as an administrative matter of governance, an ongoing business of policing what it deems to be “abnormal” or “criminal” and “lawful” and “orderly”. The enemy, whose political legitimacy is contested, is reduced to a criminal who must be punished. The resulting “policing wars” is a new mode of war that operates beyond the conventional “war” vs. “peace” or “war” vs. “crime” oppositions and has been increasingly regularized in Western military doctrine and practice.\n\nLiberal Interventionism and Crisis Governance Scaffolding Time, Space and Power in the Liberal War on Terror tells the intellectual history of the liberal war on terror, from its roots in the liberal peace debate in the 1990s, through to the intervention in Afghanistan after 9/11, to contemporary governance in crisis contexts in Libya and Syria. By tracing this development of liberal war from its early stages, through to its fully fledged post-adversarial incarnation today, the book reveals the myth of a post-adversarial war and the unintended consequences this myth produces. Through a nuanced examination of the liberal imagination, Scaffolding Time, Space and Power in the Liberal War on Terror contributes to the emerging scholarship in the field of critical war studies by exploring the implications of the liberal imagination on the logics of organised violence in the contemporary world, and in so doing, sheds light on the evolution of global governance as a liberal project.",
      "label": "Human Written",
      "ai_assistance_score": 0.004679360892623663,
      "confidence": "High",
      "start_index": 0,
      "end_index": 2017,
      "word_count": 318,
      "token_length": 405
    }
  ]
}